speciesnet/__init__.py
speciesnet/classifier.py
speciesnet/classifier_test.py
speciesnet/constants.py
speciesnet/detector.py
speciesnet/detector_test.py
speciesnet/display.py
speciesnet/ensemble.py
speciesnet/ensemble_prediction_combiner.py
speciesnet/ensemble_prediction_combiner_test.py
speciesnet/ensemble_test.py
speciesnet/geofence_utils.py
speciesnet/geofence_utils_test.py
speciesnet/geolocation.py
speciesnet/geolocation_test.py
speciesnet/multiprocessing.py
speciesnet/multiprocessing_test.py
speciesnet/taxonomy_utils.py
speciesnet/taxonomy_utils_test.py
speciesnet/utils.py
speciesnet/utils_test.py
speciesnet/scripts/build_geofence_release.py
speciesnet/scripts/gpu_test.py
speciesnet/scripts/run_model.py
speciesnet/scripts/run_server.py
speciesnet/scripts/speciesnet_to_md.py
speciesnet-5.0.3.dist-info/licenses/LICENSE
speciesnet-5.0.3.dist-info/METADATA
speciesnet-5.0.3.dist-info/WHEEL
speciesnet-5.0.3.dist-info/top_level.txt
speciesnet-5.0.3.dist-info/RECORD
