Metadata-Version: 2.4
Name: speciesnet
Version: 5.0.3
Summary: Tools for classifying species in images from motion-triggered wildlife cameras.
Author-email: Google Camera Traps AI team <cameratraps@google.com>
License-Expression: Apache-2.0
Project-URL: Homepage, https://github.com/google/cameratrapai
Project-URL: Wildlife Insights, https://www.wildlifeinsights.org
Keywords: camera traps,conservation,wildlife,ai,species classification,wildlife insights,speciesnet
Classifier: Intended Audience :: Developers
Classifier: Intended Audience :: Education
Classifier: Intended Audience :: Science/Research
Classifier: Operating System :: OS Independent
Classifier: Programming Language :: Python :: 3
Classifier: Programming Language :: Python :: 3.9
Classifier: Programming Language :: Python :: 3.10
Classifier: Programming Language :: Python :: 3.11
Classifier: Programming Language :: Python :: 3.12
Classifier: Topic :: Scientific/Engineering :: Artificial Intelligence
Classifier: Topic :: Scientific/Engineering :: Image Recognition
Requires-Python: <3.13,>=3.9
License-File: LICENSE
Requires-Dist: absl-py
Requires-Dist: cloudpathlib
Requires-Dist: huggingface_hub
Requires-Dist: humanfriendly
Requires-Dist: kagglehub
Requires-Dist: matplotlib
Requires-Dist: numpy<2.0; sys_platform == "darwin" and platform_machine == "x86_64"
Requires-Dist: numpy; sys_platform != "darwin" or platform_machine != "x86_64"
Requires-Dist: onnx2torch
Requires-Dist: pandas
Requires-Dist: pillow
Requires-Dist: requests
Requires-Dist: reverse_geocoder
Requires-Dist: tqdm
Requires-Dist: torch>=2.0
Requires-Dist: yolov5<7.0.12,>=7.0.8
Provides-Extra: az
Requires-Dist: cloudpathlib[azure]; extra == "az"
Provides-Extra: gs
Requires-Dist: cloudpathlib[gs]; extra == "gs"
Provides-Extra: s3
Requires-Dist: cloudpathlib[s3]; extra == "s3"
Provides-Extra: notebooks
Requires-Dist: ipykernel; extra == "notebooks"
Provides-Extra: server
Requires-Dist: fastapi; extra == "server"
Requires-Dist: litserve; extra == "server"
Provides-Extra: all
Requires-Dist: speciesnet[az]; extra == "all"
Requires-Dist: speciesnet[gs]; extra == "all"
Requires-Dist: speciesnet[s3]; extra == "all"
Requires-Dist: speciesnet[notebooks]; extra == "all"
Requires-Dist: speciesnet[server]; extra == "all"
Provides-Extra: dev
Requires-Dist: speciesnet[all]; extra == "dev"
Requires-Dist: black[jupyter]; extra == "dev"
Requires-Dist: isort; extra == "dev"
Requires-Dist: pylint; extra == "dev"
Requires-Dist: pymarkdownlnt; extra == "dev"
Requires-Dist: pyright; extra == "dev"
Requires-Dist: pytest; extra == "dev"
Provides-Extra: github
Requires-Dist: speciesnet[dev]; extra == "github"
Requires-Dist: pytest-custom_exit_code; extra == "github"
Dynamic: license-file
